{"cameraMode":{"drawMode":0,"name":"Shaded","section":"Shading Mode"},"sceneLighting":true,"audioPlay":false,"sceneViewState":{"m_AlwaysRefresh":false,"showFog":true,"showSkybox":true,"showFlares":true,"showImageEffects":true,"showParticleSystems":true,"showVisualEffectGraphs":true,"m_FxEnabled":false},"in2DMode":false,"pivot":{"x":5.890170574188232,"y":4.836137294769287,"z":-18.170787811279298},"rotation":{"x":0.0564858578145504,"y":-0.3347911834716797,"z":0.020139925181865693,"w":0.94044029712677},"size":0.8660253882408142,"orthographic":false}